walataint/__init__.py
walataint-0.0.2.dist-info/LICENSE
walataint-0.0.2.dist-info/METADATA
walataint-0.0.2.dist-info/WHEEL
walataint-0.0.2.dist-info/top_level.txt
walataint-0.0.2.dist-info/RECORD
