Metadata-Version: 2.1
Name: walataint
Version: 0.0.2
Summary: Primitive package for walataint
Home-page: https://github.com/Anemone95/wala-taint/
Author: anemone
Author-email: anemone95@qq.com
License: UNKNOWN
Platform: UNKNOWN
